[{"person":{"fullName":"asdasasdads","birthDate":"2008-02-09","gender":"f","age":10},"total":25,"totalTIndex":"72","totalTIndexInterpretation":"Очень значительно превышает средний","scalesWithTIndex":[{"name":"A","description":"негативное настроение","extendedDescription":"общее снижение настроения негативная оценка собственной эффективности в целом. Постоянное ожидание неприятностей, склонность к плаксивости, повышенный уровень тревожности.","value":3,"tIndex":"54","interpretation":"Средний"},{"name":"B","description":"межличностные проблемы","extendedDescription":"идентификация себя с ролью плохого, агрессивное поведение, высокий негативизм, непослушание.","value":6},{"name":"C","description":"неэффективность","extendedDescription":"высокий уровень убеждения неэффективности в школе","value":2,"tIndex":"52","interpretation":"Средний"},{"name":"D","description":"ангедония","extendedDescription":"высокий уровень истощаемости, наличие чувства базы одиночества","value":10,"tIndex":"77","interpretation":"Очень значительно превышает средний"},{"name":"E","description":"негативная самооценка","extendedDescription":"негативная оценка собственной неэффетивности, наличие суицидальных мыслей","value":4,"tIndex":"62","interpretation":"Выше среднего"}]}]